joc/__init__.py
joc/joc.py
usb_joc-0.2.0.dist-info/METADATA
usb_joc-0.2.0.dist-info/WHEEL
usb_joc-0.2.0.dist-info/top_level.txt
usb_joc-0.2.0.dist-info/RECORD
